ign_lidar/__init__.py
ign_lidar/asprs_classes.py
ign_lidar/classes.py
ign_lidar/downloader.py
ign_lidar/.mypy_cache/3.8/__future__.data.json
ign_lidar/.mypy_cache/3.8/__future__.meta.json
ign_lidar/.mypy_cache/3.8/_ast.data.json
ign_lidar/.mypy_cache/3.8/_ast.meta.json
ign_lidar/.mypy_cache/3.8/_asyncio.data.json
ign_lidar/.mypy_cache/3.8/_asyncio.meta.json
ign_lidar/.mypy_cache/3.8/_bz2.data.json
ign_lidar/.mypy_cache/3.8/_bz2.meta.json
ign_lidar/.mypy_cache/3.8/_codecs.data.json
ign_lidar/.mypy_cache/3.8/_codecs.meta.json
ign_lidar/.mypy_cache/3.8/_collections_abc.data.json
ign_lidar/.mypy_cache/3.8/_collections_abc.meta.json
ign_lidar/.mypy_cache/3.8/_compression.data.json
ign_lidar/.mypy_cache/3.8/_compression.meta.json
ign_lidar/.mypy_cache/3.8/_contextvars.data.json
ign_lidar/.mypy_cache/3.8/_contextvars.meta.json
ign_lidar/.mypy_cache/3.8/_ctypes.data.json
ign_lidar/.mypy_cache/3.8/_ctypes.meta.json
ign_lidar/.mypy_cache/3.8/_decimal.data.json
ign_lidar/.mypy_cache/3.8/_decimal.meta.json
ign_lidar/.mypy_cache/3.8/_frozen_importlib.data.json
ign_lidar/.mypy_cache/3.8/_frozen_importlib.meta.json
ign_lidar/.mypy_cache/3.8/_frozen_importlib_external.data.json
ign_lidar/.mypy_cache/3.8/_frozen_importlib_external.meta.json
ign_lidar/.mypy_cache/3.8/_io.data.json
ign_lidar/.mypy_cache/3.8/_io.meta.json
ign_lidar/.mypy_cache/3.8/_operator.data.json
ign_lidar/.mypy_cache/3.8/_operator.meta.json
ign_lidar/.mypy_cache/3.8/_pickle.data.json
ign_lidar/.mypy_cache/3.8/_pickle.meta.json
ign_lidar/.mypy_cache/3.8/_queue.data.json
ign_lidar/.mypy_cache/3.8/_queue.meta.json
ign_lidar/.mypy_cache/3.8/_random.data.json
ign_lidar/.mypy_cache/3.8/_random.meta.json
ign_lidar/.mypy_cache/3.8/_sitebuiltins.data.json
ign_lidar/.mypy_cache/3.8/_sitebuiltins.meta.json
ign_lidar/.mypy_cache/3.8/_socket.data.json
ign_lidar/.mypy_cache/3.8/_socket.meta.json
ign_lidar/.mypy_cache/3.8/_ssl.data.json
ign_lidar/.mypy_cache/3.8/_ssl.meta.json
ign_lidar/.mypy_cache/3.8/_stat.data.json
ign_lidar_hd-2.5.1.dist-info/licenses/LICENSE
ign_lidar_hd-2.5.1.dist-info/METADATA
ign_lidar_hd-2.5.1.dist-info/WHEEL
ign_lidar_hd-2.5.1.dist-info/entry_points.txt
ign_lidar_hd-2.5.1.dist-info/top_level.txt
ign_lidar_hd-2.5.1.dist-info/RECORD
