Metadata-Version: 2.4
Name: ign-lidar-hd
Version: 2.5.1
Summary: IGN LiDAR HD Dataset Processing Library for Building LOD Classification
Author-email: imagodata <simon.ducournau@gmail.com>
License-Expression: MIT
Project-URL: Homepage, https://github.com/sducournau/IGN_LIDAR_HD_DATASET
Project-URL: Repository, https://github.com/sducournau/IGN_LIDAR_HD_DATASET
Project-URL: Documentation, https://github.com/sducournau/IGN_LIDAR_HD_DATASET#readme
Project-URL: Issues, https://github.com/sducournau/IGN_LIDAR_HD_DATASET/issues
Keywords: lidar,ign,machine-learning,gis,building-classification
Classifier: Development Status :: 4 - Beta
Classifier: Intended Audience :: Developers
Classifier: Intended Audience :: Science/Research
Classifier: Operating System :: OS Independent
Classifier: Programming Language :: Python :: 3
Classifier: Programming Language :: Python :: 3.8
Classifier: Programming Language :: Python :: 3.9
Classifier: Programming Language :: Python :: 3.10
Classifier: Programming Language :: Python :: 3.11
Classifier: Programming Language :: Python :: 3.12
Classifier: Topic :: Scientific/Engineering
Classifier: Topic :: Scientific/Engineering :: GIS
Classifier: Topic :: Scientific/Engineering :: Artificial Intelligence
Requires-Python: >=3.8
License-File: LICENSE
Requires-Dist: numpy>=1.21.0
Requires-Dist: laspy>=2.3.0
Requires-Dist: lazrs>=0.5.0
Requires-Dist: scikit-learn>=1.0.0
Requires-Dist: scipy>=1.7.0
Requires-Dist: tqdm>=4.60.0
Requires-Dist: click>=8.0.0
Requires-Dist: PyYAML>=6.0
Requires-Dist: psutil>=5.8.0
Requires-Dist: hydra-core>=1.3.0
Requires-Dist: omegaconf>=2.3.0
Requires-Dist: requests>=2.25.0
Requires-Dist: Pillow>=9.0.0
Requires-Dist: h5py>=3.0.0
Provides-Extra: rgb
Requires-Dist: requests>=2.25.0; extra == "rgb"
Requires-Dist: Pillow>=9.0.0; extra == "rgb"
Provides-Extra: pipeline
Requires-Dist: PyYAML>=6.0; extra == "pipeline"
Provides-Extra: gpu
Provides-Extra: gpu-full
Requires-Dist: cuml>=23.10.0; extra == "gpu-full"
Provides-Extra: pytorch
Requires-Dist: torch>=2.0.0; extra == "pytorch"
Requires-Dist: torchvision>=0.15.0; extra == "pytorch"
Requires-Dist: torchaudio>=2.0.0; extra == "pytorch"
Provides-Extra: all
Requires-Dist: requests>=2.25.0; extra == "all"
Requires-Dist: Pillow>=9.0.0; extra == "all"
Requires-Dist: PyYAML>=6.0; extra == "all"
Provides-Extra: dev
Requires-Dist: pytest>=6.0; extra == "dev"
Requires-Dist: pytest-cov>=4.0; extra == "dev"
Requires-Dist: black>=22.0; extra == "dev"
Requires-Dist: flake8>=4.0; extra == "dev"
Requires-Dist: mypy>=0.910; extra == "dev"
Requires-Dist: build>=0.7.0; extra == "dev"
Requires-Dist: twine>=4.0; extra == "dev"
Requires-Dist: pre-commit>=2.20; extra == "dev"
Requires-Dist: requests>=2.25.0; extra == "dev"
Requires-Dist: Pillow>=9.0.0; extra == "dev"
Requires-Dist: PyYAML>=6.0; extra == "dev"
Dynamic: license-file
